lcstack/__init__.py
lcstack/base.py
lcstack/cli.py
lcstack/components/__init__.py
lcstack/components/agents/__init__.py
lcstack/components/agents/agent_supervisor.py
lcstack/components/agents/base.py
lcstack/components/agents/plan_and_execute.py
lcstack/components/agents/react_agent.py
lcstack/components/chains/__init__.py
lcstack/components/chains/base.py
lcstack/components/chat_history/__init__.py
lcstack/components/chat_history/base.py
lcstack/components/converters.py
lcstack/components/document_loaders/__init__.py
lcstack/components/document_loaders/base.py
lcstack/components/document_loaders/epub_loader.py
lcstack/components/embeddings/__init__.py
lcstack/components/embeddings/base.py
lcstack/components/indexing/__init__.py
lcstack/components/indexing/base.py
lcstack/components/languge_models/__init__.py
lcstack/components/languge_models/base.py
lcstack/components/prompts/__init__.py
lcstack/components/prompts/base.py
lcstack/components/retrievers/__init__.py
lcstack/components/retrievers/base.py
lcstack/components/text_splitters/__init__.py
lcstack/components/text_splitters/base.py
lcstack/components/tools/__init__.py
lcstack/components/tools/scrape_web.py
lcstack/components/tracers/__init__.py
lcstack/components/tracers/base.py
lcstack/components/tracers/console.py
lcstack/components/tracers/json.py
lcstack/components/tracers/logging.py
lcstack/components/vectorstores/__init__.py
lcstack/components/vectorstores/base.py
lcstack/configs.py
lcstack/core/__init__.py
lcstack/core/component.py
lcstack/core/container.py
lcstack/core/initializer.py
lcstack/core/models.py
lcstack/core/parsers/__init__.py
lcstack/core/parsers/base.py
lcstack/graph/__init__.py
lcstack/graph/base.py
lcstack/graph/conditional.py
lcstack/graph/initializer.py
lcstack/lcstack_builder.py
lcstack/registry.py
lcstack/server.py
lcstack/tracers/__init__.py
lcstack/tracers/base.py
lcstack/tracers/json.py
lcstack/tracers/logging.py
lcstack/utils.py
lcstack-0.1.1.dist-info/METADATA
lcstack-0.1.1.dist-info/WHEEL
lcstack-0.1.1.dist-info/RECORD
