Metadata-Version: 2.1
Name: lcstack
Version: 0.1.1
Summary: 
Home-page: https://github.com/bekingcn/lcstack
License: Apache
Author: Beking
Author-email: beking_cn@hotmail.com
Requires-Python: >=3.9,<4.0
Classifier: License :: Other/Proprietary License
Classifier: Programming Language :: Python :: 3
Classifier: Programming Language :: Python :: 3.9
Classifier: Programming Language :: Python :: 3.10
Classifier: Programming Language :: Python :: 3.11
Classifier: Programming Language :: Python :: 3.12
Requires-Dist: langchain (>=0.3,<0.4)
Requires-Dist: langchain-chroma (>=0.1.4)
Requires-Dist: langchain-community (>=0.3,<0.4)
Requires-Dist: langchain-google-genai (>=2)
Requires-Dist: langchain-groq (>=0.2)
Requires-Dist: langchain-huggingface (>=0.1)
Requires-Dist: langchain-ollama (>=0.2)
Requires-Dist: langchain-openai (>=0.2,<0.3)
Requires-Dist: langgraph (>=0.2.20,<0.3.0)
Requires-Dist: openai (>=1.45.0,<2.0.0)
Project-URL: Repository, https://github.com/bekingcn/lcstack
